orvixgamesapi/__init__.py
orvixgamesapi/orvixgamesapi.py
orvixgamesapi-1.0.0.dist-info/LICENSE.txt
orvixgamesapi-1.0.0.dist-info/METADATA
orvixgamesapi-1.0.0.dist-info/WHEEL
orvixgamesapi-1.0.0.dist-info/top_level.txt
orvixgamesapi-1.0.0.dist-info/RECORD
