Metadata-Version: 2.2
Name: orvixgamesapi
Version: 1.0.0
Summary: Orvix Games API ile entegrasyon sağlayan Python modülü.
Author: Orvix games
Classifier: Programming Language :: Python :: 3
Classifier: License :: OSI Approved :: MIT License
Classifier: Operating System :: OS Independent
Requires-Python: >=3.6
License-File: LICENSE.txt
Requires-Dist: requests
Dynamic: author
Dynamic: classifier
Dynamic: requires-dist
Dynamic: requires-python
Dynamic: summary
